gitllm/__init__.py
gitllm/cli.py
gitllm/git.py
simpgit-0.0.2.dist-info/METADATA
simpgit-0.0.2.dist-info/WHEEL
simpgit-0.0.2.dist-info/entry_points.txt
simpgit-0.0.2.dist-info/top_level.txt
simpgit-0.0.2.dist-info/RECORD
