Metadata-Version: 2.1
Name: simpgit
Version: 0.0.2
Summary: A tool to simplfy git operations
Maintainer-email: XetHub <contact@xethub.com>
License: BSD-3-Clause
Project-URL: Homepage, https://xethub.com/xdssio/gitlm
Keywords: ai,llm,openai,developer-tools,git,nlp
Classifier: Development Status :: 3 - Alpha
Classifier: Programming Language :: Python :: Implementation :: CPython
Classifier: Programming Language :: Python :: Implementation :: PyPy
Classifier: Programming Language :: Python
Classifier: Programming Language :: Python :: 3
Classifier: Programming Language :: Python :: 3 :: Only
Classifier: Programming Language :: Python :: 3.7
Classifier: Programming Language :: Python :: 3.8
Classifier: Programming Language :: Python :: 3.9
Classifier: Programming Language :: Python :: 3.10
Classifier: Programming Language :: Python :: 3.11
Classifier: Operating System :: POSIX :: Linux
Classifier: Operating System :: MacOS
Classifier: Topic :: Software Development :: Libraries :: Python Modules
Classifier: Topic :: System :: Filesystems
Classifier: Topic :: Software Development :: Version Control :: Git
Classifier: Topic :: Scientific/Engineering :: Artificial Intelligence
Requires-Python: >=3.7
Requires-Dist: openai (>=0.27.7)
Requires-Dist: typer (>=0.9.0)
Requires-Dist: langchain (>=0.0.191)
Requires-Dist: GitPython (>=3.1.31)
